kodegenerering/__cli__.py
kodegenerering/__init__.py
kodegenerering/__main__.py
kodegenerering/kodegenerering.py
kodegenerering-2023.10.22.dist-info/LICENSE
kodegenerering-2023.10.22.dist-info/METADATA
kodegenerering-2023.10.22.dist-info/WHEEL
kodegenerering-2023.10.22.dist-info/entry_points.txt
kodegenerering-2023.10.22.dist-info/top_level.txt
kodegenerering-2023.10.22.dist-info/RECORD
